{
  "Name": "Nami",
  "Flags": 8398080,
  "PARType": 1,
  "AssetCategory": "character",
  "MonsterDataTableID": 0,
  "RecordAsWard": false,
  "PostAttackMoveDelay": 0.0,
  "ChasingAttackRangePercent": 0.5,
  "ChampionId": 267,
  "BaseSpellEffectiveness": 0.0,
  "BaseHP": 489.32,
  "BasePAR": 377.24,
  "HPPerLevel": 74.0,
  "PARPerLevel": 43.0,
  "HPRegenPerLevel": 0.11,
  "PARRegenPerLevel": 0.08,
  "BaseStaticHPRegen": 1.0848,
  "BaseFactorHPRegen": 0.0,
  "BaseStaticPARRegen": 1.8,
  "BaseFactorPARRegen": 0.0,
  "BasePhysicalDamage": 51.208,
  "PhysicalDamagePerLevel": 3.1,
  "BaseAbilityPower": 0.0,
  "AbilityPowerIncPerLevel": 0.0,
  "BaseArmor": 19.72,
  "ArmorPerLevel": 4.0,
  "BaseSpellBlock": 30.0,
  "SpellBlockPerLevel": 0.0,
  "BaseDodge": 0.0,
  "DodgePerLevel": 0.0,
  "BaseMissChance": 0.0,
  "BaseCritChance": 0.0,
  "CritChancePerLevel": 0.0,
  "CritDamageMultiplier": 2.0,
  "BaseMoveSpeed": 335.0,
  "AttackRange": 550.0,
  "AttackAutoInterruptPercent": 0.2,
  "AcquisitionRange": 600.0,
  "AttackSpeedPerLevel": 0.026099999,
  "TowerTargetingPriority": 0.0,
  "DeathTime": -1.0,
  "GoldGivenOnDeath": 25.0,
  "ExpGivenOnDeath": 48.0,
  "GoldRadius": 0.0,
  "ExperienceRadius": 0.0,
  "DeathEventListeningRadius": 1000.0,
  "LocalGoldGivenOnDeath": 0.0,
  "LocalExpGivenOnDeath": 0.0,
  "LocalGoldSplitWithLastHitter": false,
  "GlobalGoldGivenOnDeath": 0.0,
  "GlobalExpGivenOnDeath": 0.0,
  "PerceptionBubbleRadius": 1350.0,
  "Significance": 0.0,
  "CriticalAttack": "",
  "HitFxScale": 1.0,
  "OverrideCollisionHeight": 180.0,
  "OverrideCollisionRadius": 125.0,
  "PathfindingCollisionRadius": 35.0,
  "GameplayCollisionRadius": 65.0,
  "OccludedUnitSelectableDistance": 0.0,
  "PassiveData": {
    "LuaName": "",
    "Range": 0.0
  },
  "Spells": {
    "Q": {
      "Name": "NamiQ",
      "MaxLevelOverride": 5,
      "UpgradeLevels": [
        1,
        3,
        5,
        7,
        9,
        99
      ]
    },
    "W": {
      "Name": "NamiW",
      "MaxLevelOverride": 5,
      "UpgradeLevels": [
        1,
        3,
        5,
        7,
        9,
        99
      ]
    },
    "E": {
      "Name": "NamiE",
      "MaxLevelOverride": 5,
      "UpgradeLevels": [
        1,
        3,
        5,
        7,
        9,
        99
      ]
    },
    "R": {
      "Name": "NamiR",
      "MaxLevelOverride": 3,
      "UpgradeLevels": [
        6,
        11,
        16,
        99,
        99,
        99
      ]
    }
  },
  "ExtraSpells": {
    "ExtraSpell1": "NamiRMissile",
    "ExtraSpell2": "NamiQDummyMissile",
    "ExtraSpell3": "NamiWAlly",
    "ExtraSpell4": "NamiWMissileEnemy",
    "ExtraSpell5": "NamiWMissileAlly",
    "ExtraSpell6": "NamiQMissile",
    "ExtraSpell7": "NamiWEnemy",
    "ExtraSpell8": "",
    "ExtraSpell9": "",
    "ExtraSpell10": "",
    "ExtraSpell11": "",
    "ExtraSpell12": "",
    "ExtraSpell13": "",
    "ExtraSpell14": "",
    "ExtraSpell15": "",
    "ExtraSpell16": ""
  },
  "AttacksData": {
    "BaseAttack": {
      "Name": "NamiBasicAttack",
      "Probability": 0.5,
      "DelayOffsetPercent": -0.03,
      "DelayCastOffsetPercent": -0.12,
      "DelayCastOffsetPercentAttackSpeedRatio": 1.0
    },
    "ExtraAttack1": {
      "Name": "NamiBasicAttack2",
      "Probability": 0.5,
      "DelayOffsetPercent": -0.03,
      "DelayCastOffsetPercent": -0.12,
      "DelayCastOffsetPercentAttackSpeedRatio": 1.0
    },
    "ExtraAttack2": {
      "Name": "NamiBasicAttack2",
      "Probability": 2.0,
      "DelayOffsetPercent": -0.03,
      "DelayCastOffsetPercent": -0.12,
      "DelayCastOffsetPercentAttackSpeedRatio": 1.0
    },
    "ExtraAttack3": {
      "Name": "NamiBasicAttack3",
      "Probability": 2.0,
      "DelayOffsetPercent": -0.03,
      "DelayCastOffsetPercent": -0.12,
      "DelayCastOffsetPercentAttackSpeedRatio": 1.0
    },
    "ExtraAttack4": {
      "Name": "NamiBasicAttack4",
      "Probability": 2.0,
      "DelayOffsetPercent": -0.03,
      "DelayCastOffsetPercent": -0.12,
      "DelayCastOffsetPercentAttackSpeedRatio": 1.0
    },
    "ExtraAttack5": {
      "Name": "NamiBasicAttack5",
      "Probability": 2.0,
      "DelayOffsetPercent": -0.03,
      "DelayCastOffsetPercent": -0.12,
      "DelayCastOffsetPercentAttackSpeedRatio": 1.0
    },
    "ExtraAttack6": {
      "Name": "NamiBasicAttack6",
      "Probability": 2.0,
      "DelayOffsetPercent": -0.03,
      "DelayCastOffsetPercent": -0.12,
      "DelayCastOffsetPercentAttackSpeedRatio": 1.0
    },
    "ExtraAttack7": {
      "Name": "NamiBasicAttack7",
      "Probability": 2.0,
      "DelayOffsetPercent": -0.03,
      "DelayCastOffsetPercent": -0.12,
      "DelayCastOffsetPercentAttackSpeedRatio": 1.0
    },
    "ExtraAttack8": {
      "Name": "NamiBasicAttack8",
      "Probability": 2.0,
      "DelayOffsetPercent": -0.03,
      "DelayCastOffsetPercent": -0.12,
      "DelayCastOffsetPercentAttackSpeedRatio": 1.0
    },
    "CritAttack": {
      "Name": "NamiCritAttack",
      "Probability": 2.0,
      "DelayOffsetPercent": -0.03,
      "DelayCastOffsetPercent": -0.12,
      "DelayCastOffsetPercentAttackSpeedRatio": 1.0
    },
    "ExtraCritAttack1": {
      "Name": "NamiCritAttack1",
      "Probability": 2.0,
      "DelayOffsetPercent": -0.03,
      "DelayCastOffsetPercent": -0.12,
      "DelayCastOffsetPercentAttackSpeedRatio": 1.0
    },
    "ExtraCritAttack2": {
      "Name": "NamiCritAttack2",
      "Probability": 2.0,
      "DelayOffsetPercent": -0.03,
      "DelayCastOffsetPercent": -0.12,
      "DelayCastOffsetPercentAttackSpeedRatio": 1.0
    },
    "ExtraCritAttack3": {
      "Name": "NamiCritAttack3",
      "Probability": 2.0,
      "DelayOffsetPercent": -0.03,
      "DelayCastOffsetPercent": -0.12,
      "DelayCastOffsetPercentAttackSpeedRatio": 1.0
    },
    "ExtraCritAttack4": {
      "Name": "NamiCritAttack4",
      "Probability": 2.0,
      "DelayOffsetPercent": -0.03,
      "DelayCastOffsetPercent": -0.12,
      "DelayCastOffsetPercentAttackSpeedRatio": 1.0
    },
    "ExtraCritAttack5": {
      "Name": "NamiCritAttack5",
      "Probability": 2.0,
      "DelayOffsetPercent": -0.03,
      "DelayCastOffsetPercent": -0.12,
      "DelayCastOffsetPercentAttackSpeedRatio": 1.0
    },
    "ExtraCritAttack6": {
      "Name": "NamiCritAttack6",
      "Probability": 2.0,
      "DelayOffsetPercent": -0.03,
      "DelayCastOffsetPercent": -0.12,
      "DelayCastOffsetPercentAttackSpeedRatio": 1.0
    },
    "ExtraCritAttack7": {
      "Name": "NamiCritAttack7",
      "Probability": 2.0,
      "DelayOffsetPercent": -0.03,
      "DelayCastOffsetPercent": -0.12,
      "DelayCastOffsetPercentAttackSpeedRatio": 1.0
    },
    "ExtraCritAttack8": {
      "Name": "NamiCritAttack8",
      "Probability": 2.0,
      "DelayOffsetPercent": -0.03,
      "DelayCastOffsetPercent": -0.12,
      "DelayCastOffsetPercentAttackSpeedRatio": 1.0
    }
  }
}