{
  "Name": "Amumu",
  "Flags": 8398088,
  "PARType": 1,
  "AssetCategory": "character",
  "MonsterDataTableID": 0,
  "RecordAsWard": false,
  "PostAttackMoveDelay": 0.0,
  "ChasingAttackRangePercent": 0.5,
  "ChampionId": 32,
  "BaseSpellEffectiveness": 0.0,
  "BaseHP": 613.12,
  "BasePAR": 287.2,
  "HPPerLevel": 84.0,
  "PARPerLevel": 40.0,
  "HPRegenPerLevel": 0.17,
  "PARRegenPerLevel": 0.105,
  "BaseStaticHPRegen": 1.7756,
  "BaseFactorHPRegen": 0.0,
  "BaseStaticPARRegen": 1.4764,
  "BaseFactorPARRegen": 0.0,
  "BasePhysicalDamage": 53.384,
  "PhysicalDamagePerLevel": 3.8,
  "BaseAbilityPower": 0.0,
  "AbilityPowerIncPerLevel": 0.0,
  "BaseArmor": 23.544,
  "ArmorPerLevel": 3.3,
  "BaseSpellBlock": 32.1,
  "SpellBlockPerLevel": 1.25,
  "BaseDodge": 0.0,
  "DodgePerLevel": 0.0,
  "BaseMissChance": 0.0,
  "BaseCritChance": 0.0,
  "CritChancePerLevel": 0.0,
  "CritDamageMultiplier": 2.0,
  "BaseMoveSpeed": 335.0,
  "AttackRange": 125.0,
  "AttackAutoInterruptPercent": 0.2,
  "AcquisitionRange": 600.0,
  "AttackSpeedPerLevel": 0.0218,
  "TowerTargetingPriority": 0.0,
  "DeathTime": -1.0,
  "GoldGivenOnDeath": 25.0,
  "ExpGivenOnDeath": 48.0,
  "GoldRadius": 0.0,
  "ExperienceRadius": 0.0,
  "DeathEventListeningRadius": 1000.0,
  "LocalGoldGivenOnDeath": 0.0,
  "LocalExpGivenOnDeath": 0.0,
  "LocalGoldSplitWithLastHitter": false,
  "GlobalGoldGivenOnDeath": 0.0,
  "GlobalExpGivenOnDeath": 0.0,
  "PerceptionBubbleRadius": 1350.0,
  "Significance": 0.0,
  "CriticalAttack": "",
  "HitFxScale": 1.0,
  "OverrideCollisionHeight": 130.0,
  "OverrideCollisionRadius": 100.0,
  "PathfindingCollisionRadius": 30.0,
  "GameplayCollisionRadius": 55.0,
  "OccludedUnitSelectableDistance": 0.0,
  "PassiveData": {
    "LuaName": "",
    "Range": 0.0
  },
  "Spells": {
    "Q": {
      "Name": "BandageToss",
      "MaxLevelOverride": 5,
      "UpgradeLevels": [
        1,
        3,
        5,
        7,
        9,
        99
      ]
    },
    "W": {
      "Name": "AuraofDespair",
      "MaxLevelOverride": 5,
      "UpgradeLevels": [
        1,
        3,
        5,
        7,
        9,
        99
      ]
    },
    "E": {
      "Name": "Tantrum",
      "MaxLevelOverride": 5,
      "UpgradeLevels": [
        1,
        3,
        5,
        7,
        9,
        99
      ]
    },
    "R": {
      "Name": "CurseoftheSadMummy",
      "MaxLevelOverride": 3,
      "UpgradeLevels": [
        6,
        11,
        16,
        99,
        99,
        99
      ]
    }
  },
  "ExtraSpells": {
    "ExtraSpell1": "SadMummyBandageToss",
    "ExtraSpell2": "",
    "ExtraSpell3": "",
    "ExtraSpell4": "",
    "ExtraSpell5": "",
    "ExtraSpell6": "",
    "ExtraSpell7": "",
    "ExtraSpell8": "",
    "ExtraSpell9": "",
    "ExtraSpell10": "",
    "ExtraSpell11": "",
    "ExtraSpell12": "",
    "ExtraSpell13": "",
    "ExtraSpell14": "",
    "ExtraSpell15": "",
    "ExtraSpell16": ""
  },
  "AttacksData": {
    "BaseAttack": {
      "Name": "AmumuBasicAttack",
      "Probability": 0.5,
      "DelayOffsetPercent": -0.02,
      "DelayCastOffsetPercent": 0.0,
      "DelayCastOffsetPercentAttackSpeedRatio": 1.0
    },
    "ExtraAttack1": {
      "Name": "AmumuBasicAttack2",
      "Probability": 0.5,
      "DelayOffsetPercent": -0.02,
      "DelayCastOffsetPercent": 0.0,
      "DelayCastOffsetPercentAttackSpeedRatio": 1.0
    },
    "ExtraAttack2": {
      "Name": "AmumuBasicAttack2",
      "Probability": 2.0,
      "DelayOffsetPercent": -0.02,
      "DelayCastOffsetPercent": 0.0,
      "DelayCastOffsetPercentAttackSpeedRatio": 1.0
    },
    "ExtraAttack3": {
      "Name": "AmumuBasicAttack3",
      "Probability": 2.0,
      "DelayOffsetPercent": -0.02,
      "DelayCastOffsetPercent": 0.0,
      "DelayCastOffsetPercentAttackSpeedRatio": 1.0
    },
    "ExtraAttack4": {
      "Name": "AmumuBasicAttack4",
      "Probability": 2.0,
      "DelayOffsetPercent": -0.02,
      "DelayCastOffsetPercent": 0.0,
      "DelayCastOffsetPercentAttackSpeedRatio": 1.0
    },
    "ExtraAttack5": {
      "Name": "AmumuBasicAttack5",
      "Probability": 2.0,
      "DelayOffsetPercent": -0.02,
      "DelayCastOffsetPercent": 0.0,
      "DelayCastOffsetPercentAttackSpeedRatio": 1.0
    },
    "ExtraAttack6": {
      "Name": "AmumuBasicAttack6",
      "Probability": 2.0,
      "DelayOffsetPercent": -0.02,
      "DelayCastOffsetPercent": 0.0,
      "DelayCastOffsetPercentAttackSpeedRatio": 1.0
    },
    "ExtraAttack7": {
      "Name": "AmumuBasicAttack7",
      "Probability": 2.0,
      "DelayOffsetPercent": -0.02,
      "DelayCastOffsetPercent": 0.0,
      "DelayCastOffsetPercentAttackSpeedRatio": 1.0
    },
    "ExtraAttack8": {
      "Name": "AmumuBasicAttack8",
      "Probability": 2.0,
      "DelayOffsetPercent": -0.02,
      "DelayCastOffsetPercent": 0.0,
      "DelayCastOffsetPercentAttackSpeedRatio": 1.0
    },
    "CritAttack": {
      "Name": "AmumuCritAttack",
      "Probability": 2.0,
      "DelayOffsetPercent": -0.02,
      "DelayCastOffsetPercent": 0.0,
      "DelayCastOffsetPercentAttackSpeedRatio": 1.0
    },
    "ExtraCritAttack1": {
      "Name": "AmumuCritAttack1",
      "Probability": 2.0,
      "DelayOffsetPercent": -0.02,
      "DelayCastOffsetPercent": 0.0,
      "DelayCastOffsetPercentAttackSpeedRatio": 1.0
    },
    "ExtraCritAttack2": {
      "Name": "AmumuCritAttack2",
      "Probability": 2.0,
      "DelayOffsetPercent": -0.02,
      "DelayCastOffsetPercent": 0.0,
      "DelayCastOffsetPercentAttackSpeedRatio": 1.0
    },
    "ExtraCritAttack3": {
      "Name": "AmumuCritAttack3",
      "Probability": 2.0,
      "DelayOffsetPercent": -0.02,
      "DelayCastOffsetPercent": 0.0,
      "DelayCastOffsetPercentAttackSpeedRatio": 1.0
    },
    "ExtraCritAttack4": {
      "Name": "AmumuCritAttack4",
      "Probability": 2.0,
      "DelayOffsetPercent": -0.02,
      "DelayCastOffsetPercent": 0.0,
      "DelayCastOffsetPercentAttackSpeedRatio": 1.0
    },
    "ExtraCritAttack5": {
      "Name": "AmumuCritAttack5",
      "Probability": 2.0,
      "DelayOffsetPercent": -0.02,
      "DelayCastOffsetPercent": 0.0,
      "DelayCastOffsetPercentAttackSpeedRatio": 1.0
    },
    "ExtraCritAttack6": {
      "Name": "AmumuCritAttack6",
      "Probability": 2.0,
      "DelayOffsetPercent": -0.02,
      "DelayCastOffsetPercent": 0.0,
      "DelayCastOffsetPercentAttackSpeedRatio": 1.0
    },
    "ExtraCritAttack7": {
      "Name": "AmumuCritAttack7",
      "Probability": 2.0,
      "DelayOffsetPercent": -0.02,
      "DelayCastOffsetPercent": 0.0,
      "DelayCastOffsetPercentAttackSpeedRatio": 1.0
    },
    "ExtraCritAttack8": {
      "Name": "AmumuCritAttack8",
      "Probability": 2.0,
      "DelayOffsetPercent": -0.02,
      "DelayCastOffsetPercent": 0.0,
      "DelayCastOffsetPercentAttackSpeedRatio": 1.0
    }
  }
}